shaperone/__init__.py
shaperone/_cext.cp38-win32.pyd
shaperone/_explanation.py
shaperone/_serializable.py
shaperone/datasets.py
shaperone/links.py
shaperone/actions/__init__.py
shaperone/actions/_action.py
shaperone/actions/_optimizer.py
shaperone/benchmark/__init__.py
shaperone/benchmark/_compute.py
shaperone/benchmark/_explanation_error.py
shaperone/benchmark/_result.py
shaperone/benchmark/_sequential.py
shaperone/benchmark/experiments.py
shaperone/benchmark/framework.py
shaperone/benchmark/measures.py
shaperone/benchmark/methods.py
shaperone/benchmark/metrics.py
shaperone/benchmark/models.py
shaperone/benchmark/plots.py
shaperone/cext/tree_shap.h
shaperone/explainers/__init__.py
shaperone/explainers/_additive.py
shaperone/explainers/_exact.py
shaperone/explainers/_explainer.py
shaperone/explainers/_gpu_tree.py
shaperone/explainers/_gradient.py
shaperone/explainers/_kernel.py
shaperone/explainers/_linear.py
shaperone/explainers/_partition.py
shaperone/explainers/_permutation.py
shaperone/explainers/_sampling.py
shaperone/explainers/_tree.py
shaperone/explainers/mimic.py
shaperone/explainers/pytree.py
shaperone/explainers/tf_utils.py
shaperone/explainers/_deep/__init__.py
shaperone/explainers/_deep/deep_pytorch.py
shaperone/explainers/_deep/deep_tf.py
shaperone/explainers/other/__init__.py
shaperone/explainers/other/_coefficent.py
shaperone/explainers/other/_lime.py
shaperone/explainers/other/_maple.py
shaperone/explainers/other/_random.py
shaperone/explainers/other/_treegain.py
shaperone/maskers/__init__.py
shaperone/maskers/_composite.py
shaperone/maskers/_fixed.py
shaperone/maskers/_fixed_composite.py
shaperone/maskers/_image.py
shaperone/maskers/_masker.py
shaperone/maskers/_output_composite.py
shaperone/maskers/_tabular.py
shaperone/maskers/_text.py
shaperone/models/__init__.py
shaperone/models/_model.py
shaperone/models/_teacher_forcing.py
shaperone/models/_text_generation.py
shaperone/models/_topk_lm.py
shaperone/models/_transformers_pipeline.py
shaperone-0.41.6.dist-info/LICENSE
shaperone-0.41.6.dist-info/METADATA
shaperone-0.41.6.dist-info/WHEEL
shaperone-0.41.6.dist-info/top_level.txt
shaperone-0.41.6.dist-info/RECORD
